LICENSE
MANIFEST.in
README.rst
caoe.py
setup.py
CaoE.egg-info/PKG-INFO
CaoE.egg-info/SOURCES.txt
CaoE.egg-info/dependency_links.txt
CaoE.egg-info/top_level.txt