Metadata-Version: 1.0
Name: CaoE
Version: 0.1.5
Summary: Kill all children processes when the parent dies
Home-page: https://github.com/douban/caoe
Author: Qiangning Hong
Author-email: hongqn@douban.com
License: UNKNOWN
Keywords: process management
Platform: POSIX
Classifier: Intended Audience :: Developers
Classifier: License :: OSI Approved :: BSD License
Classifier: Operating System :: POSIX
Classifier: Programming Language :: Python
